letpot/__init__.py
letpot/client.py
letpot/converters.py
letpot/deviceclient.py
letpot/exceptions.py
letpot/models.py
letpot/py.typed
letpot-0.6.2.dist-info/LICENSE.md
letpot-0.6.2.dist-info/METADATA
letpot-0.6.2.dist-info/WHEEL
letpot-0.6.2.dist-info/RECORD
