Metadata-Version: 2.3
Name: letpot
Version: 0.6.2
Summary: Asynchronous Python client for LetPot hydroponic gardens.
License: MIT
Author: Joris Pelgröm
Author-email: joris.pelgrom@gmail.com
Requires-Python: >=3.12,<4.0
Classifier: Development Status :: 3 - Alpha
Classifier: Framework :: AsyncIO
Classifier: Intended Audience :: Developers
Classifier: License :: OSI Approved :: MIT License
Classifier: Natural Language :: English
Classifier: Programming Language :: Python :: 3
Classifier: Programming Language :: Python :: 3.12
Classifier: Programming Language :: Python :: 3.13
Requires-Dist: aiohttp (>=3.11,<4.0)
Requires-Dist: aiomqtt (>=2.0,<3.0)
Project-URL: Changelog, https://github.com/jpelgrom/python-letpot/releases
Project-URL: Homepage, https://github.com/jpelgrom/python-letpot
Project-URL: Issues, https://github.com/jpelgrom/python-letpot/issues
